django_prose_editor/.gitignore
django_prose_editor/__init__.py
django_prose_editor/apps.py
django_prose_editor/checks.py
django_prose_editor/config.py
django_prose_editor/fields.py
django_prose_editor/sanitized.py
django_prose_editor/widgets.py
django_prose_editor/locale/de/LC_MESSAGES/django.mo
django_prose_editor/locale/de/LC_MESSAGES/django.po
django_prose_editor/locale/de/LC_MESSAGES/djangojs.mo
django_prose_editor/locale/de/LC_MESSAGES/djangojs.po
django_prose_editor/locale/pl/LC_MESSAGES/django.mo
django_prose_editor/locale/pl/LC_MESSAGES/django.po
django_prose_editor/locale/pl/LC_MESSAGES/djangojs.mo
django_prose_editor/locale/pl/LC_MESSAGES/djangojs.po
django_prose_editor/static/django_prose_editor/configurable.js
django_prose_editor/static/django_prose_editor/configurable.js.map
django_prose_editor/static/django_prose_editor/default.js
django_prose_editor/static/django_prose_editor/default.js.map
django_prose_editor/static/django_prose_editor/editor.css
django_prose_editor/static/django_prose_editor/editor.css.map
django_prose_editor/static/django_prose_editor/editor.js
django_prose_editor/static/django_prose_editor/editor.js.map
django_prose_editor/static/django_prose_editor/material-icons.css
django_prose_editor/static/django_prose_editor/material-icons.css.map
django_prose_editor/static/django_prose_editor/material-icons.woff2
django_prose_editor/static/django_prose_editor/overrides.css
django_prose_editor/static/django_prose_editor/overrides.css.map
django_prose_editor-0.24.0.dist-info/METADATA
django_prose_editor-0.24.0.dist-info/WHEEL
django_prose_editor-0.24.0.dist-info/licenses/LICENSE
django_prose_editor-0.24.0.dist-info/RECORD
