Metadata-Version: 2.4
Name: django-prose-editor
Version: 0.24.0
Summary: Prose editor for the Django admin based on ProseMirror
Project-URL: Documentation, https://django-prose-editor.readthedocs.io/
Project-URL: Homepage, https://github.com/matthiask/django-prose-editor/
Author-email: Matthias Kestenholz <mk@feinheit.ch>
License: BSD-3-Clause
License-File: LICENSE
Classifier: Environment :: Web Environment
Classifier: Framework :: Django
Classifier: Framework :: Django :: 4.2
Classifier: Intended Audience :: Developers
Classifier: License :: OSI Approved :: BSD License
Classifier: Operating System :: OS Independent
Classifier: Programming Language :: Python
Classifier: Programming Language :: Python :: 3 :: Only
Classifier: Programming Language :: Python :: 3.10
Classifier: Programming Language :: Python :: 3.11
Classifier: Programming Language :: Python :: 3.12
Classifier: Programming Language :: Python :: 3.13
Classifier: Programming Language :: Python :: 3.14
Classifier: Topic :: Internet :: WWW/HTTP :: Dynamic Content
Classifier: Topic :: Software Development
Classifier: Topic :: Software Development :: Libraries :: Application Frameworks
Requires-Python: >=3.10
Requires-Dist: django-js-asset>=3.1.2
Requires-Dist: django>=4.2
Provides-Extra: sanitize
Requires-Dist: nh3>=0.3; extra == 'sanitize'
Provides-Extra: tests
Requires-Dist: asgiref; extra == 'tests'
Requires-Dist: coverage; extra == 'tests'
Requires-Dist: nh3>=0.3; extra == 'tests'
Requires-Dist: pytest; extra == 'tests'
Requires-Dist: pytest-asyncio; extra == 'tests'
Requires-Dist: pytest-cov; extra == 'tests'
Requires-Dist: pytest-django; extra == 'tests'
Requires-Dist: pytest-playwright; extra == 'tests'
